{"tables":{"t1":{"label":"t1: Operating Cash Balance","name":"t1","all_cols":["table","date","year_month","year","month","day","weekday","is_total","account","account_raw","close_today","open_today","open_mo","open_fy","footnote","url"],"columns":{"date":{"name":"date","type":"TEXT","column_type":"date","item_values":[{"comparinator":">","value":"2005-06-09"},{"comparinator":"<","value":"2013-08-23"}]}}},"t2":{"label":"t2: Deposits and Withdrawals","name":"t2","all_cols":["table","date","year_month","year","month","day","weekday","account","transaction_type","parent_item","is_total","is_net","item","item_raw","today","mtd","fytd","footnote","url"],"columns":{"date":{"name":"date","type":"TEXT","column_type":"date","item_values":[{"comparinator":">","value":"2005-06-09"},{"comparinator":"<","value":"2013-08-23"}]},"transaction_type":{"name":"transaction_type","type":"TEXT","item_values":[{"comparinator":"=","value":"deposit"},{"comparinator":"=","value":"withdrawal"}]},"item":{"name":"item","type":"TEXT","item_values":[{"comparinator":"=","value":"Supplemental Security Income","parents":["deposit"]},{"comparinator":"=","value":"Agriculture Loan Repayments ( misc )","parents":["deposit"]},{"comparinator":"=","value":"Commodity Credit Corporation programs","parents":["deposit","withdrawal"]},{"comparinator":"=","value":"Customs and Certain Excise Taxes","parents":["deposit"]},{"comparinator":"=","value":"Unemployment Insurance Benefits","parents":["deposit","withdrawal"]},{"comparinator":"=","value":"Education Department programs","parents":["deposit","withdrawal"]},{"comparinator":"=","value":"Energy Department programs","parents":["deposit","withdrawal"]},{"comparinator":"=","value":"Federal Reserve Earnings","parents":["deposit"]},{"comparinator":"=","value":"Estate and Gift Taxes","parents":["deposit"]},{"comparinator":"=","value":"Interest recd from cash investments","parents":["deposit"]},{"comparinator":"=","value":"Individual Income and Employment Taxes Not Withheld","parents":["deposit"]},{"comparinator":"=","value":"Housing and Urban Development programs","parents":["deposit","withdrawal"]},{"comparinator":"=","value":"Foreign Deposits Military Sales","parents":["deposit"]},{"comparinator":"=","value":"FTDs Received","parents":["deposit"]},{"comparinator":"=","value":"Postal Service","parents":["deposit"]},{"comparinator":"=","value":"Justice Department programs","parents":["deposit","withdrawal"]},{"comparinator":"=","value":"Change in Balance of Uncollected Funds","parents":["deposit"]},{"comparinator":"=","value":"Total Other Deposits","parents":["deposit"]},{"comparinator":"=","value":"Public Debt Cash Issues ( Table III B )","parents":["deposit"]},{"comparinator":"=","value":"Transfers from Depositaries","parents":["deposit"]},{"comparinator":"=","value":"Total Federal Reserve Account","parents":["deposit","withdrawal"]},{"comparinator":"=","value":"Total Deposits ( excluding transfers )","parents":["deposit"]},{"comparinator":"=","value":"Total Tax and Loan Note Accounts Table V","parents":["deposit"]},{"comparinator":"=","value":"Transfers from Federal Reserve Account Table V","parents":["deposit"]},{"comparinator":"=","value":"Federal Employees Insurance","parents":["withdrawal","deposit"]},{"comparinator":"=","value":"Defense Vendor Payments ( EFT )","parents":["withdrawal"]},{"comparinator":"=","value":"Fed Highway Administration programs","parents":["withdrawal"]},{"comparinator":"=","value":"Federal Salaries ( EFT )","parents":["withdrawal"]},{"comparinator":"=","value":"Food Stamps","parents":["withdrawal"]},{"comparinator":"=","value":"Food and Nutrition Service ( misc )","parents":["withdrawal"]},{"comparinator":"=","value":"GSA Programs","parents":["withdrawal","deposit"]},{"comparinator":"=","value":"Health and Human Services Grants ( misc )","parents":["withdrawal"]},{"comparinator":"=","value":"Interest on Treasury Securities","parents":["withdrawal"]},{"comparinator":"=","value":"NASA programs","parents":["withdrawal"]},{"comparinator":"=","value":"Labor Dept prgms ( excl unemployment )","parents":["withdrawal"]},{"comparinator":"=","value":"Medicare","parents":["withdrawal"]},{"comparinator":"=","value":"Medicaid","parents":["withdrawal"]},{"comparinator":"=","value":"Public Debt Cash Redemp ( Table III B )","parents":["withdrawal"]},{"comparinator":"=","value":"Social Security Benefits ( EFT )","parents":["withdrawal"]},{"comparinator":"=","value":"Postal Service Money Orders and Other","parents":["withdrawal"]},{"comparinator":"=","value":"Temporary Assistance for Needy Families ( HHS )","parents":["withdrawal"]},{"comparinator":"=","value":"Veterans Affairs Programs","parents":["withdrawal"]},{"comparinator":"=","value":"Transportation Security Admin ( DHS )","parents":["withdrawal"]},{"comparinator":"=","value":"Total Other Withdrawals","parents":["withdrawal"]},{"comparinator":"=","value":"Transfers to Depositaries","parents":["withdrawal"]},{"comparinator":"=","value":"Emergency Prep Response ( DHS )","parents":["withdrawal","deposit"]},{"comparinator":"=","value":"Unclassified","parents":["withdrawal"]},{"comparinator":"=","value":"Transfers to Federal Reserve Account Table V","parents":["withdrawal"]},{"comparinator":"=","value":"Farm Credit Insurance Corp","parents":["deposit","withdrawal"]},{"comparinator":"=","value":"Total Withdrawals ( excluding transfers )","parents":["withdrawal"]},{"comparinator":"=","value":"Federal Housing Admin: Note Sales","parents":["deposit"]},{"comparinator":"=","value":"Agency for International Development","parents":["withdrawal","deposit"]},{"comparinator":"=","value":"Net Change in Operating Cash Balance","parents":["withdrawal"]},{"comparinator":"=","value":"Defense Finance Accounting Service","parents":["deposit"]},{"comparinator":"=","value":"IRS Tax Refunds Individual ( EFT )","parents":["withdrawal"]},{"comparinator":"=","value":"Federal Transit Admin","parents":["withdrawal"]},{"comparinator":"=","value":"IRS Tax Refunds Business ( EFT )","parents":["withdrawal"]},{"comparinator":"=","value":"Air Transport Security Fees","parents":["deposit"]},{"comparinator":"=","value":"Interntl Security Assistance ( DSCA )","parents":["deposit","withdrawal"]},{"comparinator":"=","value":"Military Active Duty Pay ( EFT )","parents":["withdrawal"]},{"comparinator":"=","value":"State Department","parents":["withdrawal","deposit"]},{"comparinator":"=","value":"Railroad Unemployment Ins","parents":["deposit"]},{"comparinator":"=","value":"Minerals Management Service","parents":["deposit","withdrawal"]},{"comparinator":"=","value":"Thrift Savings Plan Transfer","parents":["withdrawal","deposit"]},{"comparinator":"=","value":"HHS Deposit Fund Transfers to States","parents":["withdrawal"]},{"comparinator":"=","value":"USDA: Forest Service","parents":["withdrawal","deposit"]},{"comparinator":"=","value":"Federal Aviation Administration","parents":["withdrawal"]},{"comparinator":"=","value":"FSA Tobacco Assessments","parents":["deposit"]},{"comparinator":"=","value":"Pension Benefit Guaranty Corp","parents":["deposit","withdrawal"]},{"comparinator":"=","value":"Agriculture Loan Payments ( misc )","parents":["withdrawal"]},{"comparinator":"=","value":"Interior: Office of Territories","parents":["withdrawal"]},{"comparinator":"=","value":"Federal Financing Bank","parents":["withdrawal"]},{"comparinator":"=","value":"Export Import Bank","parents":["withdrawal","deposit"]},{"comparinator":"=","value":"Foreign Military Sales Program","parents":["withdrawal"]},{"comparinator":"=","value":"Civil Service Retirement ( EFT )","parents":["withdrawal"]},{"comparinator":"=","value":"Tennessee Valley Authority","parents":["withdrawal"]},{"comparinator":"=","value":"Military Retirement ( EFT )","parents":["withdrawal"]},{"comparinator":"=","value":"Veterans Benefits ( EFT )","parents":["withdrawal"]},{"comparinator":"=","value":"Pmt to Internat l Development Assn","parents":["withdrawal"]},{"comparinator":"=","value":"Railroad Retirement ( EFT )","parents":["withdrawal"]},{"comparinator":"=","value":"Overseas Private Investment Co","parents":["withdrawal","deposit"]},{"comparinator":"=","value":"Supple Security Income Benefits ( EFT )","parents":["withdrawal"]},{"comparinator":"=","value":"U S District Courts","parents":["withdrawal"]},{"comparinator":"=","value":"Federal Railroad Admin","parents":["withdrawal"]},{"comparinator":"=","value":"International Monetary Fund","parents":["withdrawal","deposit"]},{"comparinator":"=","value":"Pmt to Resolution Funding Corp ( Treas )","parents":["withdrawal"]},{"comparinator":"=","value":"Federal Crop Ins Corp","parents":["withdrawal"]},{"comparinator":"=","value":"Lend Lease Receipts","parents":["deposit"]},{"comparinator":"=","value":"Corps of Engineers","parents":["deposit"]},{"comparinator":"=","value":"Small Business Administration","parents":["withdrawal"]},{"comparinator":"=","value":"Interior: Bureau of Land Management","parents":["deposit","withdrawal"]},{"comparinator":"=","value":"Comptroller of the Currency Assessment","parents":["deposit"]},{"comparinator":"=","value":"Animal Plant Health Inspection svcs","parents":["deposit"]},{"comparinator":"=","value":"Bank Insurance Fund","parents":["withdrawal"]},{"comparinator":"=","value":"Ofc of Thrift Supervision ( Assessments )","parents":["deposit"]},{"comparinator":"=","value":"Securities and Exchange Commission","parents":["deposit","withdrawal"]},{"comparinator":"=","value":"Treasury Dept: Claims Payments","parents":["withdrawal"]},{"comparinator":"=","value":"Natl Railroad Retirement Inv Trust","parents":["deposit","withdrawal"]},{"comparinator":"=","value":"Centers for Disease Control","parents":["withdrawal"]},{"comparinator":"=","value":"Federal Communications Commission","parents":["deposit"]},{"comparinator":"=","value":"Small Business Admin Loan Sales","parents":["deposit"]},{"comparinator":"=","value":"Pmt to Int l Bk for Reconstruction","parents":["withdrawal"]},{"comparinator":"=","value":"Inter American Development Bank","parents":["withdrawal"]},{"comparinator":"=","value":"HHS: Indian Health Service","parents":["withdrawal"]},{"comparinator":"=","value":"SEC: Stock Exchange Fees","parents":["deposit"]},{"comparinator":"=","value":"Pmt to Corp for Pub Broadcasting","parents":["withdrawal"]},{"comparinator":"=","value":"Asset Sale: U S Enrichment Corp","parents":["deposit"]},{"comparinator":"=","value":"Gas and Oil Lease Sales Proceeds","parents":["deposit"]},{"comparinator":"=","value":"National Credit Union Administration","parents":["deposit","withdrawal"]},{"comparinator":"=","value":"Interior: Office of Surface Mining","parents":["withdrawal","deposit"]},{"comparinator":"=","value":"Library of Congress","parents":["withdrawal","deposit"]},{"comparinator":"=","value":"Fed Crop Ins Corp Fund Premiums","parents":["deposit"]},{"comparinator":"=","value":"District of Columbia","parents":["withdrawal"]},{"comparinator":"=","value":"FSLIC Resolution Fund","parents":["withdrawal","deposit"]},{"comparinator":"=","value":"Environmental Protection Agency","parents":["withdrawal","deposit"]},{"comparinator":"=","value":"FHA Debentures","parents":["withdrawal"]},{"comparinator":"=","value":"Defense Energy Supply Center","parents":["deposit"]},{"comparinator":"=","value":"Interior","parents":["withdrawal","deposit"]},{"comparinator":"=","value":"Maritime Administration","parents":["deposit","withdrawal"]},{"comparinator":"=","value":"Puerto Rico Refund of IRS Collections","parents":["withdrawal"]},{"comparinator":"=","value":"Customs and Borders Protection ( DHS )","parents":["withdrawal"]},{"comparinator":"=","value":"African Development Fund","parents":["withdrawal"]},{"comparinator":"=","value":"Prepayment of Treasury Securities","parents":["deposit","withdrawal"]},{"comparinator":"=","value":"HUD: Hurricane Relief","parents":["withdrawal"]},{"comparinator":"=","value":"Deposit Insurance Fund","parents":["withdrawal","deposit"]},{"comparinator":"=","value":"FSLIC Resolution Funds","parents":["withdrawal"]},{"comparinator":"=","value":"U S Enrichment Corp","parents":["deposit"]},{"comparinator":"=","value":"Commodity Futures Trading Commission","parents":["deposit"]},{"comparinator":"=","value":"Pmt to Resolution Funding Corp ( RTC )","parents":["withdrawal"]},{"comparinator":"=","value":"Commerce Programs","parents":["withdrawal"]},{"comparinator":"=","value":"Veterans Assets Sales","parents":["deposit"]},{"comparinator":"=","value":"Medicare Premiums","parents":["deposit"]},{"comparinator":"=","value":"Interior: Bureau of Reclamation","parents":["deposit"]},{"comparinator":"=","value":"Federal Trade Commission","parents":["deposit"]},{"comparinator":"=","value":"Presidential Election Campaign Fund","parents":["withdrawal"]},{"comparinator":"=","value":"Agriculture","parents":["withdrawal"]},{"comparinator":"=","value":"GSE Investment","parents":["withdrawal"]},{"comparinator":"=","value":"Prem ESF Money Mkt Guar Facility","parents":["deposit"]},{"comparinator":"=","value":"Capital Purchase Program ( TARP )","parents":["withdrawal"]},{"comparinator":"=","value":"Federal Finance Bank","parents":["deposit"]},{"comparinator":"=","value":"GSE Dividends","parents":["deposit"]},{"comparinator":"=","value":"TARP","parents":["withdrawal","deposit"]},{"comparinator":"=","value":"Treasury Department programs","parents":["withdrawal"]},{"comparinator":"=","value":"GSE MBS Purchase Program Income","parents":["deposit"]},{"comparinator":"=","value":"GSE Obligations HFA Initiative","parents":["withdrawal"]},{"comparinator":"=","value":"National Highway Traffic Safety Admin","parents":["withdrawal"]},{"comparinator":"=","value":"Asian Development Bank Payment","parents":["withdrawal"]}]}}},"t3a":{"label":"t3a: Public Debt Transactions","name":"t3a","all_cols":["table","date","year_month","year","month","day","weekday","transaction_type","debt_type","parent_item","is_total","item","item_raw","today","mtd","fytd","footnote","url"],"columns":{"date":{"name":"date","type":"TEXT","column_type":"date","item_values":[{"comparinator":">","value":"2005-06-09"},{"comparinator":"<","value":"2013-08-23"}]},"transaction_type":{"name":"transaction_type","type":"TEXT","item_values":[{"comparinator":"=","value":"issue"},{"comparinator":"=","value":"redemption"}]}}},"t3b":{"label":"t3b: Adjustment of Public Debt Transactions","name":"t3b","all_cols":["table","date","year_month","year","month","day","weekday","transaction_type","parent_item","is_total","item","item_raw","today","mtd","fytd","footnote","url"],"columns":{"date":{"name":"date","type":"TEXT","column_type":"date","item_values":[{"comparinator":">","value":"2005-06-09"},{"comparinator":"<","value":"2013-08-23"}]},"transaction_type":{"name":"transaction_type","type":"TEXT","item_values":[{"comparinator":"=","value":"Public Debt Cash Issues"},{"comparinator":"=","value":"Public Debt Cash Redemptions"}]}}},"t3c":{"label":"t3c: Debt Subject to Limit","name":"t3c","all_cols":["table","date","year_month","year","month","day","weekday","is_total","parent_item","item","item_raw","close_today","open_today","open_mo","open_fy","footnote","url"],"columns":{"date":{"name":"date","type":"TEXT","column_type":"date","item_values":[{"comparinator":">","value":"2005-06-09"},{"comparinator":"<","value":"2013-08-23"}]},"item":{"name":"item","type":"TEXT","item_values":[{"comparinator":"=","value":"Debt Held by the Public"},{"comparinator":"=","value":"Intragovernmental Holdings"},{"comparinator":"=","value":"Total Public Debt Outstanding"},{"comparinator":"=","value":"Other Debt"},{"comparinator":"=","value":"Unamortized Discount"},{"comparinator":"=","value":"Federal Financing Bank"},{"comparinator":"=","value":"Guaranteed Debt of Government Agencies"},{"comparinator":"=","value":"Total Public Debt Subject to Limit"},{"comparinator":"=","value":"Statutory Debt Limit"},{"comparinator":"=","value":"Repurchase Agreements"},{"comparinator":"=","value":"Hope Bonds"}]}}},"t4":{"label":"t4: Federal Tax Deposits","name":"t4","all_cols":["table","date","year_month","year","month","day","weekday","type","is_total","classification","classification_raw","today","mtd","fytd","footnote","url"],"columns":{"date":{"name":"date","type":"TEXT","column_type":"date","item_values":[{"comparinator":">","value":"2005-06-09"},{"comparinator":"<","value":"2013-08-23"}]},"classification":{"name":"classification","type":"TEXT","item_values":[{"comparinator":"=","value":"Withheld Income and Employment Taxes"},{"comparinator":"=","value":"Individual Income Taxes"},{"comparinator":"=","value":"Railroad Retirement Taxes"},{"comparinator":"=","value":"Excise Taxes"},{"comparinator":"=","value":"Corporation Income Taxes"},{"comparinator":"=","value":"Federal Unemployment Taxes"},{"comparinator":"=","value":"Estate and Gift Taxes Misc IRS Rcpts"},{"comparinator":"=","value":"Change in Balance of Unclassified Taxes"},{"comparinator":"=","value":"Total"},{"comparinator":"=","value":"Federal Reserve Account Direct"},{"comparinator":"=","value":"Federal Reserve Account Depositaries"},{"comparinator":"=","value":"Tax and Loan Accounts"},{"comparinator":"=","value":"Inter agency Transfers"},{"comparinator":"=","value":"Federal Reserve Account Total"}]}}},"t5":{"label":"t5: Short-Term Cash Investments","name":"t5","all_cols":["table","date","year_month","year","month","day","weekday","transaction_type","is_total","balance_transactions","depositary_type_a","depositary_type_b","depositary_type_c","total","footnote","url"],"columns":{"date":{"name":"date","type":"TEXT","column_type":"date","item_values":[{"comparinator":">","value":"2005-06-09"},{"comparinator":"<","value":"2012-03-30"}]},"transaction_type":{"name":"transaction_type","type":"TEXT","item_values":[{"comparinator":"=","value":"Deposits"},{"comparinator":"=","value":"Withdrawals"},{"comparinator":"=","value":"(blank)"}]}}},"t6":{"label":"t6: Income Tax Refunds Issued","name":"t6","all_cols":["table","date","year_month","year","month","day","weekday","refund_method","refund_type","refund_type_raw","today","mtd","fytd","footnote","url"],"columns":{"date":{"name":"date","type":"TEXT","column_type":"date","item_values":[{"comparinator":">","value":"2005-06-09"},{"comparinator":"<","value":"2013-08-22"}]},"refund_type":{"name":"refund_type","type":"TEXT","item_values":[{"comparinator":"=","value":"Individual"},{"comparinator":"=","value":"Business"}]}}}}}